{
  "project_info": {
    "project_number": "548685989203",
    "project_id": "final2-a569f",
    "storage_bucket": "final2-a569f.appspot.com"
  },
  "client": [
    {
      "client_info": {
        "mobilesdk_app_id": "1:548685989203:android:17b08dc0d14458cb7e4da6",
        "android_client_info": {
          "package_name": "com.example.agenda_flutter_app"
        }
      },
      "oauth_client": [],
      "api_key": [
        {
          "current_key": "AIzaSyD3xaK2dIR-yA_tYGhSOp95i89Bf3wARpE"
        }
      ],
      "services": {
        "appinvite_service": {
          "other_platform_oauth_client": []
        }
      }
    },
    {
      "client_info": {
        "mobilesdk_app_id": "1:548685989203:android:6db53bdcd80967a87e4da6",
        "android_client_info": {
          "package_name": "com.example.firebase_app"
        }
      },
      "oauth_client": [],
      "api_key": [
        {
          "current_key": "AIzaSyD3xaK2dIR-yA_tYGhSOp95i89Bf3wARpE"
        }
      ],
      "services": {
        "appinvite_service": {
          "other_platform_oauth_client": []
        }
      }
    }
  ],
  "configuration_version": "1"
}